MANIFEST.in
README.md
requirements.txt
run_proxy_ping.py
run_proxy_ping_test_suite.py
setup.py
proxy_ping/__init__.py
proxy_ping/api_view_handler.py
proxy_ping/app.py
proxy_ping/constants.py
proxy_ping/git.py
proxy_ping/git_metadata.py
proxy_ping/settings.py
proxy_ping/status_server.py
proxy_ping.egg-info/PKG-INFO
proxy_ping.egg-info/SOURCES.txt
proxy_ping.egg-info/dependency_links.txt
proxy_ping.egg-info/requires.txt
proxy_ping.egg-info/top_level.txt
proxy_ping/test/__init__.py
proxy_ping/test/test_api.py
proxy_ping/test/test_pytest.py
proxy_ping/test/test_suite.py